setup.py
figment/__init__.py
figment/cli.py
figment/component.py
figment/entity.py
figment/logger.py
figment/mode.py
figment/serializers.py
figment/utils.py
figment/zone.py
figment.egg-info/PKG-INFO
figment.egg-info/SOURCES.txt
figment.egg-info/dependency_links.txt
figment.egg-info/entry_points.txt
figment.egg-info/requires.txt
figment.egg-info/top_level.txt
tests/__init__.py
tests/helpers.py
tests/test_entity.py