Metadata-Version: 1.1
Name: figment
Version: 0.0.1
Summary: A framework for creating multiplayer, text-based worlds.
Home-page: https://github.com/vreon/figment
Author: Jesse Dubay
Author-email: jesse@jessedubay.com
License: MIT
Keywords: game engine mud
Platform: UNKNOWN
Classifier: Development Status :: 2 - Pre-Alpha
Classifier: Intended Audience :: Developers
Classifier: License :: OSI Approved :: MIT License
Classifier: Programming Language :: Python :: 2
Classifier: Programming Language :: Python :: 2.6
Classifier: Programming Language :: Python :: 2.7
Classifier: Topic :: Communications :: Chat
Classifier: Topic :: Games/Entertainment :: Multi-User Dungeons (MUD)
Classifier: Topic :: Games/Entertainment
